[
    {
        "serial":"L1",
        "type":"light_array",
        "pins":[1],
        "state":{
            "S":true
        }
    },
    {
        "serial":"L2",
        "type":"light_array",
        "pins":[2],
        "state":{
            "S":true
        }
    },
    {
        "serial":"L3",
        "type":"light_array",
        "pins":[3],
        "state":{
            "S":false
        }
    },
    {
        "serial":"F1",
        "type":"fan",
        "pins":[4],
        "state":{
            "S":true
        }
    },
    {
        "serial":"F2",
        "type":"fan",
        "pins":[5],
        "state":{
            "S":true
        }
    },
    {
        "serial":"F3",
        "type":"fan",
        "pins":[6],
        "state":{
            "S":true
        }
    },
    {
        "serial":"F4",
        "type":"fan",
        "pins":[7],
        "state":{
            "S":true
        }
    },
    {
        "serial":"AC1",
        "type":"ac",
        "pins":[8],
        "state":{
            "S":true,
            "T":24
        }
    },
    {
        "serial":"AC2",
        "type":"ac",
        "pins":[9],
        "state":{
            "S":true,
            "T":24
        }
    },
    {
        "serial":"AC3",
        "type":"ac",
        "pins":[10],
        "state":{
            "S":true,
            "T":24
        }
    },
    {
        "serial":"ZAL",
        "type":"zone",
        "pins":[1,2,3],
        "state":{
            "S":false
        }
    },
    {
        "serial":"ZAF",
        "type":"zone",
        "pins":[4,5,6,7],
        "state":{
            "S":true
        }
    },
    {
        "serial":"ZAAC",
        "type":"zone",
        "pins":[8,9,10],
        "state":{
            "S":true
        }
    }
]